craft_detector/__init__.py
craft_detector/craft.py
craft_detector/craft_utils.py
craft_detector/file_utils.py
craft_detector/imgproc.py
craft_detector/refinenet.py
craft_detector/basenet/__init__.py
craft_detector/basenet/vgg16_bn.py
craft_detector/utils/logging.py
craft_detector/utils/utils.py
craft_detector-0.2.1.dist-info/METADATA
craft_detector-0.2.1.dist-info/WHEEL
craft_detector-0.2.1.dist-info/licenses/LICENSE
craft_detector-0.2.1.dist-info/RECORD
