Metadata-Version: 2.4
Name: craft-detector
Version: 0.2.1
Summary: Python package for Official implementation of Character Region Awareness for Text Detection (CRAFT)
Author-email: "Clova AI Research, NAVER Corp." <youngmin.baek@navercorp.com>
Maintainer-email: Won-Kyu Park <wkpark@gmail.com>
License-Expression: MIT
License-File: LICENSE
Keywords: craft,deep-learning,machine-learning,ml,pytorch,text,text-detection
Classifier: Development Status :: 5 - Production/Stable
Classifier: Intended Audience :: Developers
Classifier: Intended Audience :: Science/Research
Classifier: Operating System :: OS Independent
Classifier: Programming Language :: Python :: 3
Classifier: Topic :: Education
Classifier: Topic :: Scientific/Engineering
Classifier: Topic :: Scientific/Engineering :: Artificial Intelligence
Classifier: Topic :: Scientific/Engineering :: Image Recognition
Classifier: Topic :: Software Development :: Libraries
Classifier: Topic :: Software Development :: Libraries :: Python Modules
Requires-Python: >=3.10
Requires-Dist: opencv-python>=4.10.0
Requires-Dist: scikit-image>=0.25.1
Requires-Dist: scipy>=1.14.0
Requires-Dist: torch>=2.1.2
Requires-Dist: torchvision>=0.17.2
